pixtools/__init__.py
pixtools/audio_player.py
pixtools/cache.py
pixtools/image_gen.py
pixtools/openaiclient.py
pixtools/text_to_speech.py
pixtools/voice_recorder.py
pixtools-0.1.1.dist-info/METADATA
pixtools-0.1.1.dist-info/WHEEL
pixtools-0.1.1.dist-info/top_level.txt
pixtools-0.1.1.dist-info/RECORD
