Metadata-Version: 2.4
Name: pixtools
Version: 0.1.1
Summary: A collection of multimedia utilities for AI-powered applications
Author-email: Jonas Minnberg <sasq64@gmail.com>
License: MIT
Project-URL: Homepage, https://github.com/sasq64/pixtools
Project-URL: Repository, https://github.com/sasq64/pixtools
Project-URL: Issues, https://github.com/sasq64/pixtools/issues
Keywords: ai,multimedia,openai,text-to-speech,image-generation
Classifier: Development Status :: 3 - Alpha
Classifier: Intended Audience :: Developers
Classifier: License :: OSI Approved :: MIT License
Classifier: Programming Language :: Python :: 3
Classifier: Programming Language :: Python :: 3.10
Classifier: Programming Language :: Python :: 3.11
Classifier: Programming Language :: Python :: 3.12
Classifier: Programming Language :: Python :: 3.13
Classifier: Topic :: Multimedia
Classifier: Topic :: Software Development :: Libraries :: Python Modules
Requires-Python: >=3.10
Requires-Dist: openai>=1.0.0
Requires-Dist: pyaudio>=0.2.11
Requires-Dist: pillow>=10.0.0
Provides-Extra: dev
Requires-Dist: pytest>=7.0; extra == "dev"
Requires-Dist: pytest-mock>=3.0; extra == "dev"
Requires-Dist: ruff>=0.1.0; extra == "dev"
Requires-Dist: pyright>=1.1.0; extra == "dev"
